bioprops/__init__.py
bioprops/cell_properties.py
bioprops/colony_properties.py
BioProps-0.1.0.dist-info/METADATA
BioProps-0.1.0.dist-info/WHEEL
BioProps-0.1.0.dist-info/top_level.txt
BioProps-0.1.0.dist-info/RECORD
