Metadata-Version: 2.1
Name: BioProps
Version: 0.1.0
Summary: A Python library for computing properties of cell nuclei and colonies from NIfTI files, enabling analysis of cellular structures in medical images.
Home-page: https://github.com/sohaibcs1/bioprops
Author: Muhammad Sohaib
Author-email: sohaib.cs1@gmail.com
License: UNKNOWN
Platform: UNKNOWN
Classifier: Programming Language :: Python :: 3
Classifier: License :: OSI Approved :: MIT License
Classifier: Operating System :: OS Independent
Requires-Python: >=3.6
Requires-Dist: numpy
Requires-Dist: nibabel
Requires-Dist: scipy
Requires-Dist: scikit-image
